{
    "gs3j": "2026-02-23",
    "s3qa": "2026-02-25",
    "s2yh": "2026-02-25",
    "x8em": "2026-02-26",
    "w227": "2026-02-23",
    "s9ed": "2026-02-26",
    "s3et": "2026-02-24",
    "s4ve": "2026-02-23",
    "jjxw": "2026-02-24",
    "psty": "2026-02-24",
    "s5cj": "2026-02-24",
    "t0qo": "2026-02-23",
    "t5rz": "2026-02-24",
    "oksi": "2026-02-25",
    "s9mg": "2026-02-26",
    "s4ki": "2026-02-25",
    "s2zn": "2026-02-24",
    "p66p": "2026-02-23",
    "s3dj": "2026-02-23",
    "t2ml": "2026-02-26",
    "u3bd": "2026-02-23",
    "lb5h": "2026-02-25",
    "c4vv": "2026-02-26",
    "s6ua": "2026-02-23",
    "s0wl": "2026-02-25",
    "b41r": "2026-02-26",
    "z614": "2026-02-24",
    "t1bc": "2026-02-24",
    "st1p": "2026-02-25",
    "xgcz": "2026-02-23",
    "s2ti": "2026-02-23",
    "s9it": "2026-02-26",
    "dkot": "2026-02-25",
    "k22m": "2026-02-24",
    "pz6t": "2026-02-26",
    "s3xz": "2026-02-24",
    "mdea": "2026-02-25",
    "twyj": "2026-02-24",
    "y16s": "2026-02-24",
    "t0va": "2026-02-24",
    "f7ht": "2026-02-26",
    "u9uk": "2026-02-26",
    "s6so": "2026-02-25",
    "klch": "2026-02-25",
    "s4lh": "2026-02-21",
    "ps7w": "2026-02-23",
    "aus6": "2026-02-26",
    "s8dn": "2026-02-23",
    "ucb4": "2026-02-24",
    "hpso": "2026-02-23",
    "s6ea": "2026-02-23",
    "cst3": "2026-02-26",
    "oy5p": "2026-02-24",
    "wwr9": "2026-02-25",
    "s2ll": "2026-02-26",
    "w8cg": "2026-02-24",
    "s7hw": "2026-02-25",
    "yo5g": "2026-02-22",
    "rbiy": "2026-02-26",
    "u5sa": "2026-02-26",
    "otkz": "2026-02-25",
    "u2ky": "2026-02-24",
    "dbll": "2026-02-26",
    "t1ez": "2026-02-26",
    "wols": "2026-02-22",
    "s2rx": "2026-02-26",
    "mkb6": "2026-02-23",
    "s5vb": "2026-02-24",
    "s1id": "2026-02-24",
    "u2qd": "2026-02-24",
    "ds8t": "2026-02-26",
    "v2vg": "2026-02-26",
    "duvw": "2026-02-25",
    "s7zv": "2026-02-23",
    "o1yu": "2026-02-23",
    "hxzu": "2026-02-24",
    "atyu": "2026-02-25",
    "s2nb": "2026-02-26",
    "t5dw": "2026-02-26",
    "suyc": "2026-02-26",
    "pojr": "2026-02-25",
    "s8mp": "2026-02-25",
    "t6zm": "2026-02-25",
    "s8ev": "2026-02-24",
    "s9rc": "2026-02-26",
    "pw9e": "2026-02-24",
    "s8lk": "2026-02-25",
    "uf3u": "2026-02-24",
    "v4kd": "2026-02-26",
    "u2mp": "2026-02-21",
    "w1v1": "2026-02-25",
    "pm5l": "2026-02-26",
    "toy2": "2026-02-26",
    "s2dj": "2026-02-26",
    "y5ch": "2026-02-23",
    "k9of": "2026-02-24",
    "s1qf": "2026-02-25",
    "k5du": "2026-02-25",
    "olci": "2026-02-23",
    "p3r0": "2026-02-26",
    "ea63": "2026-02-24",
    "t8dz": "2026-02-23",
    "s2xc": "2026-02-25",
    "nc8g": "2026-02-26",
    "kpds": "2026-02-22",
    "c9m0": "2026-02-24",
    "wvzp": "2026-02-25",
    "qbvn": "2026-02-24",
    "eo3p": "2026-02-25",
    "w632": "2026-02-25",
    "sqhd": "2026-02-23",
    "sqak": "2026-02-25",
    "s7kn": "2026-02-24",
    "s3kp": "2026-02-25",
    "u9sa": "2026-02-24",
    "qjga": "2026-02-24",
    "s4nw": "2026-02-23",
    "t2ul": "2026-02-25",
    "xg4y": "2026-02-26",
    "cqe6": "2026-02-25",
    "o3ss": "2026-02-24",
    "s7zi": "2026-02-24",
    "r26z": "2026-02-19",
    "u4zo": "2026-02-24",
    "la44": "2026-02-24",
    "n2qt": "2026-02-23",
    "foia": "2026-02-26",
    "zen3": "2026-02-24",
    "t7lv": "2026-02-25",
    "a2ni": "2026-02-24",
    "skhi": "2026-02-26",
    "s8ea": "2026-02-26",
    "d5bl": "2026-02-25",
    "yufs": "2026-02-26",
    "s6nh": "2026-02-26",
    "zwpd": "2026-02-24",
    "mm4y": "2026-02-22",
    "pusc": "2026-02-25",
    "gune": "2026-02-25",
    "l88b": "2026-02-22",
    "s685": "2026-02-23",
    "s4lt": "2026-02-26",
    "t5xx": "2026-02-19",
    "mvz4": "2026-02-26",
    "u7ou": "2026-02-23",
    "e5sg": "2026-02-25",
    "oy0s": "2026-02-23",
    "cxdq": "2026-02-23",
    "u8xl": "2026-02-24",
    "s3se": "2026-02-26",
    "bwtk": "2026-02-23",
    "i7uc": "2026-02-24",
    "d9xl": "2026-02-26",
    "t7tu": "2026-02-26",
    "vc3r": "2026-02-26",
    "d6kv": "2026-02-26",
    "n2qc": "2026-02-24",
    "s5bo": "2026-02-24",
    "z1hj": "2026-02-25",
    "klxh": "2026-02-22",
    "erpq": "2026-02-25",
    "h2f2": "2026-02-22",
    "jhdc": "2026-02-26",
    "eome": "2026-02-25",
    "qpt6": "2026-02-22",
    "uj76": "2026-02-25",
    "p186": "2026-02-26",
    "y925": "2026-02-24",
    "u2rc": "2026-02-23",
    "tiz6": "2026-02-23",
    "s9sd": "2026-02-24",
    "rqek": "2026-02-25",
    "tey3": "2026-02-26",
    "n6af": "2026-02-24",
    "y33d": "2026-02-26",
    "u9xd": "2026-02-25",
    "s0wa": "2026-02-25",
    "kdop": "2026-02-25",
    "ra54": "2026-02-23",
    "s2nl": "2026-02-22",
    "p0pg": "2026-02-25",
    "zy4g": "2026-02-22",
    "v83g": "2026-02-25",
    "s4ip": "2026-02-26",
    "u0mi": "2026-02-25",
    "mbsh": "2026-02-23",
    "j1l8": "2026-02-24",
    "s2om": "2026-02-25",
    "bccp": "2026-02-22",
    "ljzb": "2026-02-24",
    "vvfr": "2026-02-23",
    "evp2": "2026-02-26",
    "haa1": "2026-02-26",
    "jc93": "2026-02-24",
    "t7yr": "2026-02-24",
    "u9ow": "2026-02-21",
    "qk62": "2026-02-24",
    "olmz": "2026-02-24",
    "s7jm": "2026-02-23",
    "s3ny": "2026-02-25",
    "acn9": "2026-02-25",
    "s7hi": "2026-02-23",
    "s9de": "2026-02-25",
    "x8xi": "2026-02-24",
    "qo3m": "2026-02-22",
    "xqmm": "2026-02-25",
    "nsan": "2026-02-23",
    "d6k0": "2026-02-26",
    "cpbk": "2026-02-25",
    "f1w5": "2026-02-22",
    "l8ae": "2026-02-24",
    "j7qe": "2026-02-25",
    "n5aj": "2026-02-24",
    "iyuu": "2026-02-26",
    "h0ow": "2026-02-23",
    "rtxb": "2026-02-24",
    "q0ji": "2026-02-26",
    "xx0k": "2026-02-23",
    "u0ni": "2026-02-25",
    "eq10": "2026-02-26",
    "s5gh": "2026-02-25",
    "styd": "2026-02-24",
    "wils": "2026-02-26",
    "nmgs": "2026-02-23",
    "b6i9": "2026-02-26",
    "l3s6": "2026-02-23",
    "m4f7": "2026-02-23",
    "kwzq": "2026-02-25",
    "pwi1": "2026-02-22",
    "s2an": "2026-02-24",
    "x3aw": "2026-02-24",
    "s3qh": "2026-02-26",
    "k5te": "2026-02-26",
    "ho0l": "2026-02-23",
    "cqb1": "2026-02-21",
    "u6fs": "2026-02-26",
    "lpag": "2026-02-22",
    "hubq": "2026-02-26",
    "hl01": "2026-02-26",
    "gldd": "2026-02-26",
    "ptbp": "2026-02-24",
    "a378": "2026-02-26",
    "s9az": "2026-02-24",
    "z30a": "2026-02-25",
    "s6nc": "2026-02-25",
    "fzqa": "2026-02-25",
    "eph0": "2026-02-20",
    "lh6q": "2026-02-25",
    "cv8h": "2026-02-26",
    "kfni": "2026-02-25",
    "upge": "2026-02-23",
    "m8yt": "2026-02-24",
    "x6wl": "2026-02-22",
    "t1gq": "2026-02-25",
    "an57": "2026-02-25",
    "ar6y": "2026-02-25",
    "ejzc": "2026-02-25",
    "hbgy": "2026-02-23",
    "pz5g": "2026-02-24",
    "iw9k": "2026-02-24",
    "s00k": "2026-02-26",
    "u2ft": "2026-02-23",
    "i6qb": "2026-02-24",
    "wfn8": "2026-02-24",
    "s5gr": "2026-02-26",
    "qtek": "2026-02-24",
    "u6jz": "2026-02-25",
    "izvp": "2026-02-25",
    "ph2k": "2026-02-24",
    "wphd": "2026-02-25",
    "x3wx": "2026-02-25",
    "o75t": "2026-02-23",
    "ujq1": "2026-02-26",
    "x3ui": "2026-02-23",
    "t5h7": "2026-02-24",
    "btyr": "2026-02-24",
    "v9l6": "2026-02-26",
    "wld1": "2026-02-26",
    "s1og": "2026-02-24",
    "ndec": "2026-02-26",
    "m371": "2026-02-24",
    "injz": "2026-02-24",
    "s2pr": "2026-02-24",
    "on1b": "2026-02-25",
    "q5du": "2026-02-25",
    "lf2o": "2026-02-22",
    "k0lc": "2026-02-23",
    "ilyr": "2026-02-25",
    "g35l": "2026-02-25",
    "wuxi": "2026-02-24",
    "mj26": "2026-02-26",
    "k5ww": "2026-02-26",
    "hdr3": "2026-02-26",
    "s3wh": "2026-02-25",
    "wy5x": "2026-02-22",
    "l835": "2026-02-23",
    "p945": "2026-02-23",
    "wgm6": "2026-02-22",
    "vdrs": "2026-02-23",
    "k0fy": "2026-02-26",
    "mkxc": "2026-02-25",
    "s5fk": "2026-02-25",
    "pny2": "2026-02-26",
    "s6fq": "2026-02-25",
    "f80g": "2026-02-26",
    "g3hv": "2026-02-24",
    "dws9": "2026-02-26",
    "jx0o": "2026-02-25",
    "rzst": "2026-02-26",
    "pgpv": "2026-02-24",
    "v0uh": "2026-02-24",
    "c1i0": "2026-02-26",
    "bcjg": "2026-02-24",
    "ig7k": "2026-02-23",
    "lyun": "2026-02-26",
    "uvpm": "2026-02-22",
    "k8nj": "2026-02-22",
    "jymf": "2026-02-22",
    "zhbi": "2026-02-24",
    "bvf1": "2026-02-26",
    "filb": "2026-02-26",
    "f4hh": "2026-02-22",
    "x3l0": "2026-02-25",
    "k0pm": "2026-02-25",
    "nrbc": "2026-02-26",
    "v7iw": "2026-02-26",
    "d3om": "2026-02-26",
    "uzzh": "2026-02-24",
    "oh2h": "2026-02-24",
    "ghtn": "2026-02-25",
    "ki9u": "2026-02-26",
    "h5lo": "2026-02-23",
    "irmi": "2026-02-21",
    "gn0j": "2026-02-25",
    "rfjk": "2026-02-24",
    "esde": "2026-02-25",
    "sj6j": "2026-02-25",
    "p7au": "2026-02-24",
    "l21b": "2026-02-23",
    "tknf": "2026-02-26",
    "reaq": "2026-02-26",
    "hfvz": "2026-02-25",
    "s5lv": "2026-02-23",
    "t547": "2026-02-25",
    "kd7l": "2026-02-26",
    "s7yw": "2026-02-26",
    "xmxx": "2026-02-23",
    "ba49": "2026-02-26",
    "iqiv": "2026-02-24",
    "ipop": "2026-02-25",
    "s0pl": "2026-02-24",
    "qmuh": "2026-02-24",
    "tx5y": "2026-02-25",
    "lfyq": "2026-02-25",
    "ln0c": "2026-02-23",
    "zly8": "2026-02-26",
    "t2zt": "2026-02-23",
    "a2y0": "2026-02-24",
    "u0fu": "2026-02-23",
    "e3ze": "2026-02-23",
    "nij5": "2026-02-25",
    "f4tf": "2026-02-24",
    "e2fm": "2026-02-24",
    "yy3d": "2026-02-26",
    "t0bz": "2026-02-25",
    "d3o8": "2026-02-24",
    "posn": "2026-02-23",
    "y2dl": "2026-02-24",
    "x4mi": "2026-02-23",
    "u06s": "2026-02-25",
    "xw7b": "2026-02-25",
    "n7us": "2026-02-24",
    "iyrm": "2026-02-24",
    "suds": "2026-02-22",
    "bm7c": "2026-02-23",
    "m3hk": "2026-02-26",
    "yegr": "2026-02-24",
    "t8xa": "2026-02-24",
    "fvjp": "2026-02-23",
    "rjbp": "2026-02-24",
    "m92a": "2026-02-26",
    "p8xn": "2026-02-25",
    "e2vv": "2026-02-21",
    "lmzn": "2026-02-24",
    "i1kn": "2026-02-25",
    "jzby": "2026-02-24",
    "f7c4": "2026-02-24",
    "u4nd": "2026-02-25",
    "th8d": "2026-02-26",
    "d9jk": "2026-02-26",
    "kh1q": "2026-02-25",
    "tk6d": "2026-02-21",
    "aqc5": "2026-02-25",
    "lvn8": "2026-02-26",
    "s9kh": "2026-02-24",
    "luzf": "2026-02-22",
    "x2t4": "2026-02-25",
    "d4t8": "2026-02-23",
    "r7h7": "2026-02-26",
    "ecdn": "2026-02-26"
}